napari_bud_cell_segmenter/__init__.py
napari_bud_cell_segmenter/_reader.py
napari_bud_cell_segmenter/_sample_data.py
napari_bud_cell_segmenter/_widget.py
napari_bud_cell_segmenter/_writer.py
napari_bud_cell_segmenter/napari.yaml
napari_bud_cell_segmenter/_tests/__init__.py
napari_bud_cell_segmenter/_tests/test_reader.py
napari_bud_cell_segmenter/_tests/test_sample_data.py
napari_bud_cell_segmenter/_tests/test_widget.py
napari_bud_cell_segmenter/_tests/test_writer.py
napari_bud_cell_segmenter-0.1.4.dist-info/LICENSE
napari_bud_cell_segmenter-0.1.4.dist-info/METADATA
napari_bud_cell_segmenter-0.1.4.dist-info/WHEEL
napari_bud_cell_segmenter-0.1.4.dist-info/entry_points.txt
napari_bud_cell_segmenter-0.1.4.dist-info/top_level.txt
napari_bud_cell_segmenter-0.1.4.dist-info/RECORD
