Metadata-Version: 2.1
Name: napari-bud-cell-segmenter
Version: 0.1.4
Summary: A plugin to segment embryonic mammary bud cells and detect 2 RNA probes
Home-page: https://github.com/AurelienMaillot/napari-bud-cell-segmenter
Author: Aurelien Maillot
Author-email: aurelien.maillot@protonmail.com
License: BSD-3-Clause
Project-URL: Bug Tracker, https://github.com/AurelienMaillot/napari-bud-cell-segmenter/issues
Project-URL: Documentation, https://github.com/AurelienMaillot/napari-bud-cell-segmenter#README.md
Project-URL: Source Code, https://github.com/AurelienMaillot/napari-bud-cell-segmenter
Project-URL: User Support, https://github.com/AurelienMaillot/napari-bud-cell-segmenter/issues
Classifier: Development Status :: 2 - Pre-Alpha
Classifier: Framework :: napari
Classifier: Intended Audience :: Developers
Classifier: License :: OSI Approved :: BSD License
Classifier: Operating System :: OS Independent
Classifier: Programming Language :: Python
Classifier: Programming Language :: Python :: 3
Classifier: Programming Language :: Python :: 3 :: Only
Classifier: Programming Language :: Python :: 3.8
Classifier: Programming Language :: Python :: 3.9
Classifier: Programming Language :: Python :: 3.10
Classifier: Topic :: Scientific/Engineering :: Image Processing
Requires-Python: >=3.8
License-File: LICENSE
Requires-Dist: numpy
Requires-Dist: magicgui
Requires-Dist: qtpy
Requires-Dist: pandas
Requires-Dist: scikit-image
Requires-Dist: napari
Requires-Dist: tifffile
Requires-Dist: matplotlib
Requires-Dist: scipy
Provides-Extra: testing
Requires-Dist: tox ; extra == 'testing'
Requires-Dist: pytest ; extra == 'testing'
Requires-Dist: pytest-cov ; extra == 'testing'
Requires-Dist: pytest-qt ; extra == 'testing'
Requires-Dist: napari ; extra == 'testing'
Requires-Dist: pyqt5 ; extra == 'testing'
